{
  "attachments": [],
  "headers": {},
  "headerLines": [
    {
      "key": "received",
      "line": "Received: from AM0PR09MB4436.eurprd09.prod.outlook.com (2603:10a6:20b:149::19)\r\n by AM6PR09MB2408.eurprd09.prod.outlook.com with HTTPS; Thu, 7 Mar 2024\r\n 08:09:37 +0000"
    },
    {
      "key": "received",
      "line": "Received: from DM6PR08CA0021.namprd08.prod.outlook.com (2603:10b6:5:80::34) by\r\n AM0PR09MB4436.eurprd09.prod.outlook.com (2603:10a6:20b:149::19) with\r\n Microsoft SMTP Server (version=TLS1_2,\r\n cipher=TLS_ECDHE_RSA_WITH_AES_256_GCM_SHA384) id 15.20.7339.39; Thu, 7 Mar\r\n 2024 08:09:36 +0000"
    },
    {
      "key": "received",
      "line": "Received: from CH3PEPF0000000F.namprd04.prod.outlook.com\r\n (2603:10b6:5:80:cafe::6a) by DM6PR08CA0021.outlook.office365.com\r\n (2603:10b6:5:80::34) with Microsoft SMTP Server (version=TLS1_2,\r\n cipher=TLS_ECDHE_RSA_WITH_AES_256_GCM_SHA384) id 15.20.7362.26 via Frontend\r\n Transport; Thu, 7 Mar 2024 08:09:35 +0000"
    },
    {
      "key": "authentication-results",
      "line": "Authentication-Results: spf=pass (sender IP is 209.85.219.182)\r\n smtp.mailfrom=gmail.com; dkim=pass (signature was verified)\r\n header.d=gmail.com;dmarc=pass action=none header.from=gmail.com;compauth=pass\r\n reason=100"
    },
    {
      "key": "received-spf",
      "line": "Received-SPF: Pass (protection.outlook.com: domain of gmail.com designates\r\n 209.85.219.182 as permitted sender) receiver=protection.outlook.com;\r\n client-ip=209.85.219.182; helo=mail-yb1-f182.google.com; pr=C"
    },
    {
      "key": "received",
      "line": "Received: from mail-yb1-f182.google.com (209.85.219.182) by\r\n CH3PEPF0000000F.mail.protection.outlook.com (10.167.244.40) with Microsoft\r\n SMTP Server (version=TLS1_2, cipher=TLS_ECDHE_RSA_WITH_AES_256_GCM_SHA384) id\r\n 15.20.7362.11 via Frontend Transport; Thu, 7 Mar 2024 08:09:35 +0000"
    },
    {
      "key": "x-incomingtopheadermarker",
      "line": "X-IncomingTopHeaderMarker:\r\n OriginalChecksum:352DBE63028411FFC40B9A30E0F95FEFDB9762EC4F8A4F8404F7E2AD9D0788D4;UpperCasedChecksum:042E0913F1756C8D463F3C5686B698A44E4B63CD43EE88EA055E907FE70EE4FB;SizeAsReceived:2659;Count:15"
    },
    {
      "key": "received",
      "line": "Received: by mail-yb1-f182.google.com with SMTP id 3f1490d57ef6-dcc80d6006aso659306276.0\r\n        for <justdev001@outlook.com>; Thu, 07 Mar 2024 00:09:35 -0800 (PST)"
    },
    {
      "key": "dkim-signature",
      "line": "DKIM-Signature: v=1; a=rsa-sha256; c=relaxed/relaxed;\r\n        d=gmail.com; s=20230601; t=1709798975; x=1710403775; darn=outlook.com;\r\n        h=to:subject:message-id:date:from:in-reply-to:references:mime-version\r\n         :from:to:cc:subject:date:message-id:reply-to;\r\n        bh=YxyIPk17HZzVX73sxLLlm+Cr4jUCGyCgLfNctHfZf2U=;\r\n        b=hyPPITWEvC/zv53VwE3xwcNpS1aT9Ya8MlPTFcVD72uppxF8oFGnNta412k/8eQTIF\r\n         3aKxH9LgaFVv//QdGCZVH9DyPAsBB9tyXB6a+VFJ4LWEz9KzQvVtwNAyay9FF78MuZ1/\r\n         CcqTcwr1kJliL0X49laPGP+y2usDqEIJrB+ajUFbqkXI77WF1vDGBekGq5GGcHN7X2js\r\n         lUzZVD9M9KbU9vujYeXCxvCgo/YwOK0T8oeYVfh/u2mnzNNxSBj0AFWNCoeqWiMJp6iH\r\n         YvnurtuJtBFI7wVssy2EWYQCbaNLQnaA0wLyDBXhJVvmeemg71KwJdKzkbmbUovQqeas\r\n         A92Q=="
    },
    {
      "key": "x-google-dkim-signature",
      "line": "X-Google-DKIM-Signature: v=1; a=rsa-sha256; c=relaxed/relaxed;\r\n        d=1e100.net; s=20230601; t=1709798975; x=1710403775;\r\n        h=to:subject:message-id:date:from:in-reply-to:references:mime-version\r\n         :x-gm-message-state:from:to:cc:subject:date:message-id:reply-to;\r\n        bh=YxyIPk17HZzVX73sxLLlm+Cr4jUCGyCgLfNctHfZf2U=;\r\n        b=EMolgJY244VPn9MQkXTwNEDHvf7ouG1RzcwCHaBQEqVqHqkEWvki5uJwNbBAjczEcM\r\n         NjEOvc2XXuJkcfosCP+dpOVOZYZmt1ZWUesFDkU45PUgInoSm5JU/xHPmuVyVtjCJaMR\r\n         2b1JZr1YHDL9i0Usbp1bGLLHKve+MQfd6OEuFg+KuAnoZ+UFkV59YEkZZyE+aGoh1bKD\r\n         l8SGz7H7PrB9HxAQmx4REow7OGGg6SMUx1Ue3Nm21Xj26rzLXHY5rq2U/dYBwP017odP\r\n         07J4XkgFuA/ZCPBlA06MP18YDXLKmyO7PsbUxhNqSWFRGr6p7kCebvahS/ytJvhPZNUI\r\n         QP+g=="
    },
    {
      "key": "x-gm-message-state",
      "line": "X-Gm-Message-State: AOJu0Yz92Hj4iZmDh+hKsbdvGUnu+cNrMTscwhOEVwEEnLMrHzU3qREg\r\n\t5jZ1X6SG8Xy7WkQ+LvauRQPGt85RmhcQgI+KM7I7Os+1aDoOXvphA5Q2apf139UD7x32M+g0QT5\r\n\t8SLRd5KCxW1ky/bUPYQ8+w25ugAITei0ZRhZHjmXD"
    },
    {
      "key": "x-google-smtp-source",
      "line": "X-Google-Smtp-Source: AGHT+IFssPXcuxuzy+4wmdk9paJFCE7Y7+7vfXSfWaCvEf3xGbCsxzbClT099Xsuz/aknEBi2QEeRLde4+S/UXMif5c="
    },
    {
      "key": "x-received",
      "line": "X-Received: by 2002:a05:6902:250a:b0:dc7:46e7:7aea with SMTP id\r\n dt10-20020a056902250a00b00dc746e77aeamr16049427ybb.47.1709798975417; Thu, 07\r\n Mar 2024 00:09:35 -0800 (PST)"
    },
    {
      "key": "references",
      "line": "References: <AM6PR09MB2408CC92F349ED5BF911938A82202@AM6PR09MB2408.eurprd09.prod.outlook.com>"
    },
    {
      "key": "in-reply-to",
      "line": "In-Reply-To: <AM6PR09MB2408CC92F349ED5BF911938A82202@AM6PR09MB2408.eurprd09.prod.outlook.com>"
    },
    {
      "key": "from",
      "line": "From: justdev email <justdev001.email@gmail.com>"
    },
    { "key": "date", "line": "Date: Thu, 7 Mar 2024 13:09:24 +0500" },
    {
      "key": "message-id",
      "line": "Message-ID: <CAPrYACWS4p=wQipXEj_yGzXSPYzLHNZAAf1o=URUHoOaR04Abw@mail.gmail.com>"
    },
    { "key": "subject", "line": "Subject: Re: Hello world" },
    { "key": "to", "line": "To: justdev001@outlook.com" },
    {
      "key": "content-type",
      "line": "Content-Type: multipart/alternative; boundary=\"000000000000913aa406130d98de\""
    },
    { "key": "x-incomingheadercount", "line": "X-IncomingHeaderCount: 15" },
    { "key": "return-path", "line": "Return-Path: justdev001.email@gmail.com" },
    {
      "key": "x-ms-exchange-organization-expirationstarttime",
      "line": "X-MS-Exchange-Organization-ExpirationStartTime: 07 Mar 2024 08:09:35.8380\r\n (UTC)"
    },
    {
      "key": "x-ms-exchange-organization-expirationstarttimereason",
      "line": "X-MS-Exchange-Organization-ExpirationStartTimeReason: OriginalSubmit"
    },
    {
      "key": "x-ms-exchange-organization-expirationinterval",
      "line": "X-MS-Exchange-Organization-ExpirationInterval: 1:00:00:00.0000000"
    },
    {
      "key": "x-ms-exchange-organization-expirationintervalreason",
      "line": "X-MS-Exchange-Organization-ExpirationIntervalReason: OriginalSubmit"
    },
    {
      "key": "x-ms-exchange-organization-network-message-id",
      "line": "X-MS-Exchange-Organization-Network-Message-Id:\r\n 7f1fdfb3-e3de-487d-693a-08dc3e7deda1"
    },
    { "key": "x-eopattributedmessage", "line": "X-EOPAttributedMessage: 0" },
    {
      "key": "x-eoptenantattributedmessage",
      "line": "X-EOPTenantAttributedMessage: 84df9e7f-e9f6-40af-b435-aaaaaaaaaaaa:0"
    },
    {
      "key": "x-ms-exchange-organization-messagedirectionality",
      "line": "X-MS-Exchange-Organization-MessageDirectionality: Incoming"
    },
    {
      "key": "x-ms-publictraffictype",
      "line": "X-MS-PublicTrafficType: Email"
    },
    {
      "key": "x-ms-traffictypediagnostic",
      "line": "X-MS-TrafficTypeDiagnostic:\r\n CH3PEPF0000000F:EE_|AM0PR09MB4436:EE_|AM6PR09MB2408:EE_"
    },
    {
      "key": "x-ms-exchange-organization-authsource",
      "line": "X-MS-Exchange-Organization-AuthSource:\r\n CH3PEPF0000000F.namprd04.prod.outlook.com"
    },
    {
      "key": "x-ms-exchange-organization-authas",
      "line": "X-MS-Exchange-Organization-AuthAs: Anonymous"
    },
    {
      "key": "x-ms-userlastlogontime",
      "line": "X-MS-UserLastLogonTime: 3/7/2024 8:07:29 AM"
    },
    {
      "key": "x-ms-office365-filtering-correlation-id",
      "line": "X-MS-Office365-Filtering-Correlation-Id: 7f1fdfb3-e3de-487d-693a-08dc3e7deda1"
    },
    {
      "key": "x-ms-exchange-eopdirect",
      "line": "X-MS-Exchange-EOPDirect: true"
    },
    { "key": "x-sender-ip", "line": "X-Sender-IP: 209.85.219.182" },
    { "key": "x-sid-pra", "line": "X-SID-PRA: JUSTDEV001.EMAIL@GMAIL.COM" },
    { "key": "x-sid-result", "line": "X-SID-Result: PASS" },
    {
      "key": "x-ms-exchange-organization-pcl",
      "line": "X-MS-Exchange-Organization-PCL: 2"
    },
    {
      "key": "x-ms-exchange-organization-scl",
      "line": "X-MS-Exchange-Organization-SCL: 1"
    },
    { "key": "x-microsoft-antispam", "line": "X-Microsoft-Antispam: BCL:0;" },
    {
      "key": "x-ms-exchange-crosstenant-originalarrivaltime",
      "line": "X-MS-Exchange-CrossTenant-OriginalArrivalTime: 07 Mar 2024 08:09:35.8067\r\n (UTC)"
    },
    {
      "key": "x-ms-exchange-crosstenant-network-message-id",
      "line": "X-MS-Exchange-CrossTenant-Network-Message-Id: 7f1fdfb3-e3de-487d-693a-08dc3e7deda1"
    },
    {
      "key": "x-ms-exchange-crosstenant-id",
      "line": "X-MS-Exchange-CrossTenant-Id: 84df9e7f-e9f6-40af-b435-aaaaaaaaaaaa"
    },
    {
      "key": "x-ms-exchange-crosstenant-authsource",
      "line": "X-MS-Exchange-CrossTenant-AuthSource:\r\n CH3PEPF0000000F.namprd04.prod.outlook.com"
    },
    {
      "key": "x-ms-exchange-crosstenant-authas",
      "line": "X-MS-Exchange-CrossTenant-AuthAs: Anonymous"
    },
    {
      "key": "x-ms-exchange-crosstenant-fromentityheader",
      "line": "X-MS-Exchange-CrossTenant-FromEntityHeader: Internet"
    },
    {
      "key": "x-ms-exchange-crosstenant-rms-persistedconsumerorg",
      "line": "X-MS-Exchange-CrossTenant-RMS-PersistedConsumerOrg:\r\n 00000000-0000-0000-0000-000000000000"
    },
    {
      "key": "x-ms-exchange-transport-crosstenantheadersstamped",
      "line": "X-MS-Exchange-Transport-CrossTenantHeadersStamped: AM0PR09MB4436"
    },
    {
      "key": "x-ms-exchange-transport-endtoendlatency",
      "line": "X-MS-Exchange-Transport-EndToEndLatency: 00:00:01.9861496"
    },
    {
      "key": "x-ms-exchange-processed-by-bccfoldering",
      "line": "X-MS-Exchange-Processed-By-BccFoldering: 15.20.7339.034"
    },
    {
      "key": "x-microsoft-antispam-mailbox-delivery",
      "line": "X-Microsoft-Antispam-Mailbox-Delivery:\r\n\tucf:0;jmr:0;ex:0;auth:1;dest:I;OFR:SpamFilterPass;ENG:(5062000305)(920221119095)(90000117)(920221120095)(90013020)(91025020)(91040095)(9050020)(9060121)(9100341)(1010050)(944500132)(4810010)(4910033)(9920006)(9510006)(10105021)(9320005)(9230038)(120001);"
    },
    {
      "key": "x-message-info",
      "line": "X-Message-Info:\r\n\tqZelhIiYnPmJltQbTh+9hDBKEmv8a+mE8q1wTGHA9RYrHMXUNXtfzdK022c4rZOMjid/9mv87foDYsWnJ2mG51CiU2uRJadgWaQiiW0003hq2Z7pTpO6tiYKJ28pn3UA1S5wiaK6TAicGoE8WakSO9xCQntuG+OCG2xRqjxmV2gDPr4kGukARA47YDjNHdFeNIkxK5CGr7bcx3WC5//eLQ=="
    },
    {
      "key": "x-message-delivery",
      "line": "X-Message-Delivery: Vj0xLjE7dXM9MDtsPTA7YT0xO0Q9MTtHRD0xO1NDTD0tMQ=="
    },
    {
      "key": "x-microsoft-antispam-message-info",
      "line": "X-Microsoft-Antispam-Message-Info:\r\n\t=?utf-8?B?M1ZXbUxqandEZndnZWNSM0dPeHdEUEs2dVlKczd0MWlYYWVQSGRkTStCdHNE?=\r\n =?utf-8?B?NHVDOGZ6WVhpMjlZdTUwbnBkVEFwaHcyYlNZOHNhZ2VCeGRkMjJ4UFMwSDBC?=\r\n =?utf-8?B?OHAwOEd3NzM0NzRpU3gyZ2RrZWlpWVpZV3FyQTZXZkFRUTZpV0JSZlhJdHB4?=\r\n =?utf-8?B?U1ZFdWFleTRvcjRybTRqNUx4cTRRZ09hcjE2Z25pODBpekRCR3g4MWMzSGhP?=\r\n =?utf-8?B?RkQwVGxWSzcycnplT0F0YU53VlQvK0lSUEVhSlZOKzRFUEpIQzg2dWhPa2hZ?=\r\n =?utf-8?B?N2pWRTJVRlBIZHpvMGE0OWF2d1ZUVWJlMjVkK3dMRWI0cnVQQW9WWExjU0h6?=\r\n =?utf-8?B?dGNKU3RMOVpHK1QrenNDMGhSUm5hbDJxSzZJNGd0bkpUWVVxbjQwWXlhQkFH?=\r\n =?utf-8?B?OXBMTVFnVHpQcEQ2ZlRCWjNLZTE2WFBtL04rcnJqeDIySFE5QnpXbXlnUGdG?=\r\n =?utf-8?B?cGtGaUcrK0ZFU1Fqd2RMWFFvaVRBeHU3YmRaZmZVTXNQQmcwNzg4b3VzcTJN?=\r\n =?utf-8?B?dEJOK3g3RHpheDJGK2UvQVJCOCtKdE95eDFwYTRkN3hEQUptczRMeThxVG0y?=\r\n =?utf-8?B?VHhaak9CdjJSRGsvdmczNmNZZDNMQW1vUFVvUHVvV3hmeWhnRGRRdENuWVdr?=\r\n =?utf-8?B?b29VT3NIRUMzbUp3N0V6eGUxZ09wOWlhSXIrOWwrc3RSdkRhSlFUdHlueG1y?=\r\n =?utf-8?B?bmRXM2JEQWtVN1pJV0I3OWRkSmlzNEp1MklLcFBDQ3E4OSt5bHFYK24zMkFF?=\r\n =?utf-8?B?RUVFdFN0ODhSdkZ2R3VoUlJMVXRzWXU3Y3UycE5LWlhFWXlvZkZUQkhYSUFB?=\r\n =?utf-8?B?dVNXRUZCem9xd0Q3cUwraDBrUUJ6OW8vM0ZPTkxvekYvVmhKTDZtanVxekhG?=\r\n =?utf-8?B?MUg5ay9TaVV1LzR3VFJNdDh1eVZqUWRoNFhEeHk3MUlObWErdGd5Y2c3czhw?=\r\n =?utf-8?B?SC8xa2RnTjJkam94d2IyWDVzeFdkZ3pPemRWNmlHNzcyVEE4SmV6YUZvVXpm?=\r\n =?utf-8?B?cXgwUTRZZGpEZ2RZS2hrWWJrRVUvSUQ0cmdQZEllWTJhVnV5N0E0MzVBV1ls?=\r\n =?utf-8?B?T2hzWFV3VGhkS25Yc2lKVkN6SEhYQjdIdDAwVk51ZVNWVmh2WllxdGVvV3Q2?=\r\n =?utf-8?B?Zk4zbllDV0xqSmZlUVZDQ09ZUEtCQVJWWFBHZnlXZFpNVFl1bWVsT3dtYmtO?=\r\n =?utf-8?B?Vi9nYzVuQy9XQ3VvZWwrZGhhR1BnTkJ6WW9tZFRrZEJsMkdQRFZGL05Kc2lW?=\r\n =?utf-8?B?SVJIUnNBbldWQy9VZkJQSWFOK1BnNXBDS3VmVnQ0Rk16NVlvUnY0UjF0UXEw?=\r\n =?utf-8?B?Y3MzdTRRajVtVjdRM0lHeVRKWHlQM3dJc2VyWTNhd1BQZktzanpZeVE5MUJt?=\r\n =?utf-8?B?c3NRVmpVaXY1ckxSdkVVWjdOblJlTCsyYWd1ZWM4SUtSYXJPVkVvQ241bnlu?=\r\n =?utf-8?B?c3Byc1hSRHBaWlZlUEI2OU9QUllnRkhDK3lEemVJenB1ZkwwSVZBMk5xcXEw?=\r\n =?utf-8?B?ajNwZkNRcnBqazEwUDdVMm5hbTdvM0pCMUtURlB2Szd4d0w3T3FnOHVpK0VQ?=\r\n =?utf-8?B?RGFmVzF0aUgycXhBQzUzdUlkWXFybGh4TUlHQUNLcW1wQ1lSSVhYdFo1dXRK?=\r\n =?utf-8?B?bHAxUlFsMDNvNmlQMWZZWlQySktMZ1hZY1hoUDR3SmY4dmVlWlMyT3hSVXhF?=\r\n =?utf-8?B?VzlRY2JWSWxUZjBtTHZ2c0NocWwvZkQyeW1xVWdwMGp6VTlIWDVUcnlibWFr?=\r\n =?utf-8?B?M1JWRmRZcVlWTFZPYTc2bXNhVnNPaUtKdEFKK1VEd2ZHTjFDLzAvam44Wks3?=\r\n =?utf-8?B?d3NTYkVkR3FBVWVCSUU5QUFSUHlXWXdoTjRmWlVadGhJazdmVmgzYnlLWkpL?=\r\n =?utf-8?B?dlp1ckZiZmFMUHlKVFZ4d3ZWTmNKcEZ0L1J1MU93dXBzSmNYa1lKU2ZOeTNL?=\r\n =?utf-8?B?NU5vNGxwYVdJQnRWandOY2xjYlB4MnFOUTJuNmw3TzZQb2NOeWtTdEJkbXZx?=\r\n =?utf-8?B?WkRRU1p4QUdXLzViK05CUXV4NmZta3Z2Wmk1cHk4QXpPdTY4dTA4bHhqdm5y?=\r\n =?utf-8?B?SEhBTWlWek9hMEthV2o2ajltSTNaQUw0MnFuczY2eHVBV1VEV0FUU2JLZGpZ?=\r\n =?utf-8?B?bEc4OW5EdFpjNjk1U3FueUdKNU13cW43cUsrMSt2UVdpVWFBQUtvdlppQU9H?=\r\n =?utf-8?B?bXBBSnJUQXVlcDR5UUFxcUVYMWVQSk1tdHNGSDZFOHN3NTRPNHBEM0ZjT09o?=\r\n =?utf-8?B?NWRCZlN2bUM1R21zaCs2cGxnMEErVkZENkRJQUQzL3g5enpCZ1ZMdm9WYkgz?=\r\n =?utf-8?B?bFhaL1laZ3E2c3dLT1Vpc0x4YjExbTRNbldGWFVTY2ZvTjMyTFI0ZDN5MDhx?=\r\n =?utf-8?B?Y0J5UmtaOENKTWVaVmJkd2g0NWJyRHMxVjN0YktFb0sycEdXYmlTV0YxOTFw?=\r\n =?utf-8?B?SFRBQzRiMExGMXBndGxnZ2kyS2tESGRneHNidEwxQXN2enNSN0V3bGkvQnNF?=\r\n =?utf-8?B?MS95bzFKZ1UydEF3K29XN1B2cGs0NERwNFVicjJXRU9qcGlFUGZlVm1JUnUy?=\r\n =?utf-8?Q?X4oZ3gvwM=3D?="
    },
    { "key": "mime-version", "line": "MIME-Version: 1.0" }
  ],
  "html": "<meta http-equiv=\"Content-Type\" content=\"text/html; charset=utf-8\"><div dir=\"ltr\">Szija Hello</div><br><div class=\"gmail_quote\"><div dir=\"ltr\" class=\"gmail_attr\">On Thu, Mar 7, 2024 at 1:08 PM &lt;<a href=\"mailto:justdev001@outlook.com\">justdev001@outlook.com</a>&gt; wrote:<br></div><blockquote class=\"gmail_quote\" style=\"margin:0px 0px 0px 0.8ex;border-left:1px solid rgb(204,204,204);padding-left:1ex\">Original Sender: &quot;Patrik Takacs&quot; &lt;<a href=\"mailto:takacspatrik993@gmail.com\" target=\"_blank\">takacspatrik993@gmail.com</a>&gt;<br>\n<br>\nHi<br>\n</blockquote></div>\n",
  "text": "Szija Hello\n\nOn Thu, Mar 7, 2024 at 1:08 PM <justdev001@outlook.com> wrote:\n\n> Original Sender: \"Patrik Takacs\" <takacspatrik993@gmail.com>\n>\n> Hi\n>\n",
  "textAsHtml": "<p>Szija Hello</p><p>On Thu, Mar 7, 2024 at 1:08&#x202F;PM &lt;<a href=\"mailto:justdev001@outlook.com\">justdev001@outlook.com</a>&gt; wrote:</p><p>&gt; Original Sender: &quot;Patrik Takacs&quot; &lt;<a href=\"mailto:takacspatrik993@gmail.com\">takacspatrik993@gmail.com</a>&gt;<br/>&gt;<br/>&gt; Hi<br/>&gt;</p>",
  "subject": "Re: Hello world",
  "references": "<AM6PR09MB2408CC92F349ED5BF911938A82202@AM6PR09MB2408.eurprd09.prod.outlook.com>",
  "date": "2024-03-07T08:09:24.000Z",
  "to": {
    "value": [{ "address": "justdev001@outlook.com", "name": "" }],
    "html": "<span class=\"mp_address_group\"><a href=\"mailto:justdev001@outlook.com\" class=\"mp_address_email\">justdev001@outlook.com</a></span>",
    "text": "justdev001@outlook.com"
  },
  "from": {
    "value": [
      { "address": "justdev001.email@gmail.com", "name": "justdev email" }
    ],
    "html": "<span class=\"mp_address_group\"><span class=\"mp_address_name\">justdev email</span> &lt;<a href=\"mailto:justdev001.email@gmail.com\" class=\"mp_address_email\">justdev001.email@gmail.com</a>&gt;</span>",
    "text": "\"justdev email\" <justdev001.email@gmail.com>"
  },
  "messageId": "<CAPrYACWS4p=wQipXEj_yGzXSPYzLHNZAAf1o=URUHoOaR04Abw@mail.gmail.com>",
  "inReplyTo": "<AM6PR09MB2408CC92F349ED5BF911938A82202@AM6PR09MB2408.eurprd09.prod.outlook.com>"
}
